<?xml version="1.0" encoding="UTF-8"?>

<PluginState version="1.0.0" preset="Rush Beat">
  <PARAMETERS>
    <PARAM id="accent" value="0.0"/>
    <PARAM id="decayeq_band1_bypass" value="0.0"/>
    <PARAM id="decayeq_band1_freq" value="46.0"/>
    <PARAM id="decayeq_band1_gain" value="0.9599990844726562"/>
    <PARAM id="decayeq_band1_mode" value="2.0"/>
    <PARAM id="decayeq_band1_q" value="0.7099999785423279"/>
    <PARAM id="decayeq_band2_bypass" value="0.0"/>
    <PARAM id="decayeq_band2_freq" value="252.0"/>
    <PARAM id="decayeq_band2_gain" value="0.0"/>
    <PARAM id="decayeq_band2_mode" value="1.0"/>
    <PARAM id="decayeq_band2_q" value="0.7099999785423279"/>
    <PARAM id="decayeq_band3_bypass" value="0.0"/>
    <PARAM id="decayeq_band3_freq" value="1587.0"/>
    <PARAM id="decayeq_band3_gain" value="0.0"/>
    <PARAM id="decayeq_band3_mode" value="1.0"/>
    <PARAM id="decayeq_band3_q" value="0.7099999785423279"/>
    <PARAM id="decayeq_band4_bypass" value="0.0"/>
    <PARAM id="decayeq_band4_freq" value="2029.0"/>
    <PARAM id="decayeq_band4_gain" value="-9.840000152587891"/>
    <PARAM id="decayeq_band4_mode" value="2.0"/>
    <PARAM id="decayeq_band4_q" value="0.7099999785423279"/>
    <PARAM id="diff_amt" value="0.0"/>
    <PARAM id="diff_path" value="0.0"/>
    <PARAM id="diff_size" value="0.0"/>
    <PARAM id="dist_bias" value="0.0"/>
    <PARAM id="dist_color" value="0.0"/>
    <PARAM id="dist_drive" value="1.0"/>
    <PARAM id="dist_dyn" value="0.0"/>
    <PARAM id="dist_mode" value="0.0"/>
    <PARAM id="dist_post" value="0.0"/>
    <PARAM id="dist_pre" value="0.3400000035762787"/>
    <PARAM id="dist_trim" value="-12.0"/>
    <PARAM id="duck_amt" value="0.0"/>
    <PARAM id="duck_atk" value="5.000000476837158"/>
    <PARAM id="duck_hld" value="0.0"/>
    <PARAM id="duck_rel" value="500.0"/>
    <PARAM id="duck_thres" value="0.9990000128746033"/>
    <PARAM id="feedback" value="0.4399999976158142"/>
    <PARAM id="feel" value="-1.0"/>
    <PARAM id="flutter_depth" value="0.2999999821186066"/>
    <PARAM id="flutter_rate" value="0.9999998807907104"/>
    <PARAM id="haas_width" value="0.03320002555847168"/>
    <PARAM id="inputeq_band1_bypass" value="0.0"/>
    <PARAM id="inputeq_band1_freq" value="40.0"/>
    <PARAM id="inputeq_band1_gain" value="0.0"/>
    <PARAM id="inputeq_band1_mode" value="1.0"/>
    <PARAM id="inputeq_band1_q" value="0.7099999785423279"/>
    <PARAM id="inputeq_band2_bypass" value="0.0"/>
    <PARAM id="inputeq_band2_freq" value="252.0"/>
    <PARAM id="inputeq_band2_gain" value="0.0"/>
    <PARAM id="inputeq_band2_mode" value="1.0"/>
    <PARAM id="inputeq_band2_q" value="0.7099999785423279"/>
    <PARAM id="inputeq_band3_bypass" value="0.0"/>
    <PARAM id="inputeq_band3_freq" value="1451.0"/>
    <PARAM id="inputeq_band3_gain" value="10.79999923706055"/>
    <PARAM id="inputeq_band3_mode" value="1.0"/>
    <PARAM id="inputeq_band3_q" value="3.049999952316284"/>
    <PARAM id="inputeq_band4_bypass" value="0.0"/>
    <PARAM id="inputeq_band4_freq" value="9999.9990234375"/>
    <PARAM id="inputeq_band4_gain" value="0.0"/>
    <PARAM id="inputeq_band4_mode" value="1.0"/>
    <PARAM id="inputeq_band4_q" value="0.7099999785423279"/>
    <PARAM id="link" value="1.0"/>
    <PARAM id="mix" value="0.3199999928474426"/>
    <PARAM id="mod_depth" value="0.2999999821186066"/>
    <PARAM id="mod_rate" value="0.72489994764328"/>
    <PARAM id="mode" value="0.0"/>
    <PARAM id="pan_dry" value="0.5"/>
    <PARAM id="pan_wet" value="0.5"/>
    <PARAM id="pipo_width" value="1.0"/>
    <PARAM id="pitch_mix" value="1.0"/>
    <PARAM id="pitch_mode" value="1.0"/>
    <PARAM id="pitch_path" value="0.0"/>
    <PARAM id="pitch_shift" value="0.0"/>
    <PARAM id="rate_l" value="0.4999999701976776"/>
    <PARAM id="rate_r" value="0.4999999701976776"/>
    <PARAM id="rate_sync_l" value="3.0"/>
    <PARAM id="rate_sync_r" value="3.0"/>
    <PARAM id="stereo" value="1.0"/>
    <PARAM id="swing" value="0.0"/>
    <PARAM id="sync_l" value="1.0"/>
    <PARAM id="sync_r" value="1.0"/>
    <PARAM id="tape_amt" value="0.0"/>
    <PARAM id="wow_depth" value="0.2999999821186066"/>
    <PARAM id="wow_drift" value="0.25"/>
    <PARAM id="wow_rate" value="0.9999998807907104"/>
    <PARAM id="wow_var" value="0.25"/>
  </PARAMETERS>
</PluginState>
